Workbook

Sheet retail_sales_2023
A1: Order_ID | B1: Order_Date | C1: Customer_ID | D1: Customer_Name | E1: Region | F1: Category | G1: Product_Name | H1: Quantity | I1: Unit_Price | J1: Discount | K1: Sales | L1: Profit | M1: Revenue | N1: Quarter | O1: Profit Percentage | P1: City | Q1: Segment
A2: ORD006312 | B2: 45065 | C2: CUST0260 | D2: Timothy Nori | E2: South | F2: Books | G2: Excel for Beginners | H2: 3 | I2: 671.24 | J2: 0 | K2: 2013.72 | L2: 689.84 | M2: =H2*I2*(1-J2) -> 2013.72 | N2: ="Q"&ROUNDUP(MONTH(B2)/3,0) -> Q2 | O2: =(L2/K2)*100 -> 34.256997 | P2: =VLOOKUP(retail_sales_2023!C2,customers!A:J,5,) -> Kochi | Q2: =VLOOKUP(C2,customers!A:J,10,0) -> Regular
A3: ORD008688 | B3: 45066 | C3: CUST0223 | D3: Aarini Dugar | E3: East | F3: Furniture | G3: Wooden Study Table | H3: 3 | I3: 21336.22 | J3: 0 | K3: 64008.66 | L3: 16168.33 | M3: =H3*I3*(1-J3) -> 64008.66 | N3: ="Q"&ROUNDUP(MONTH(B3)/3,0) -> Q2 | O3: =(L3/K3)*100 -> 25.259598 | P3: =VLOOKUP(retail_sales_2023!C3,customers!A:J,5,) -> Guwahati | Q3: =VLOOKUP(C3,customers!A:J,10,0) -> Premium
A4: ORD007579 | B4: 45137 | C4: CUST0258 | D4: Sanaya Khalsa | E4: North | F4: Sports | G4: Running Shoes | H4: 1 | I4: 649.49 | J4: 0.3 | K4: 454.64 | L4: 126.47 | M4: =H4*I4*(1-J4) -> 454.643 | N4: ="Q"&ROUNDUP(MONTH(B4)/3,0) -> Q3 | O4: =(L4/K4)*100 -> 27.817614 | P4: =VLOOKUP(retail_sales_2023!C4,customers!A:J,5,) -> Delhi | Q4: =VLOOKUP(C4,customers!A:J,10,0) -> Premium
A5: ORD004768 | B5: 45017 | C5: CUST0037 | D5: Janani Sawhney | E5: West | F5: Furniture | G5: Shoe Rack | H5: 4 | I5: 41779.66 | J5: 0.2 | K5: 133694.91 | L5: 39801.41 | M5: =H5*I5*(1-J5) -> 133694.91 | N5: ="Q"&ROUNDUP(MONTH(B5)/3,0) -> Q2 | O5: =(L5/K5)*100 -> 29.770326 | P5: =VLOOKUP(retail_sales_2023!C5,customers!A:J,5,) -> Ahmedabad | Q5: =VLOOKUP(C5,customers!A:J,10,0) -> Premium
A6: ORD006089 | B6: 45137 | C6: CUST0044 | D6: Advay Nadig | E6: North | F6: Toys | G6: Board Game Monopoly | H6: 5 | I6: 3035.91 | J6: 0.05 | K6: 14420.57 | L6: 2873.99 | M6: =H6*I6*(1-J6) -> 14420.572 | N6: ="Q"&ROUNDUP(MONTH(B6)/3,0) -> Q3 | O6: =(L6/K6)*100 -> 19.929795 | P6: =VLOOKUP(retail_sales_2023!C6,customers!A:J,5,) -> Lucknow | Q6: =VLOOKUP(C6,customers!A:J,10,0) -> Premium
A7: ORD004604 | B7: 45073 | C7: CUST0221 | D7: Naveen Dass | E7: South | F7: Electronics | G7: 4K Smart TV | H7: 4 | I7: 25815.94 | J7: 0.05 | K7: 98100.57 | L7: 11250.48 | M7: =H7*I7*(1-J7) -> 98100.572 | N7: ="Q"&ROUNDUP(MONTH(B7)/3,0) -> Q2 | O7: =(L7/K7)*100 -> 11.468313 | P7: =VLOOKUP(retail_sales_2023!C7,customers!A:J,5,) -> Kochi | Q7: =VLOOKUP(C7,customers!A:J,10,0) -> Regular
A8: ORD007001 | B8: 45016 | C8: CUST0435 | D8: Ekalinga Chowdhury | E8: East | F8: Toys | G8: LEGO City Set | H8: 5 | I8: 2120.52 | J8: 0 | K8: 10602.6 | L8: 3680.74 | M8: =H8*I8*(1-J8) -> 10602.6 | N8: ="Q"&ROUNDUP(MONTH(B8)/3,0) -> Q1 | O8: =(L8/K8)*100 -> 34.715447 | P8: =VLOOKUP(retail_sales_2023!C8,customers!A:J,5,) -> Bhubaneswar | Q8: =VLOOKUP(C8,customers!A:J,10,0) -> Premium
A9: ORD005992 | B9: 44942 | C9: CUST0266 | D9: Tanay Sane | E9: East | F9: Groceries | G9: Sunflower Oil 1L | H9: 4 | I9: 496.51 | J9: 0 | K9: 1986.04 | L9: 198.32 | M9: =H9*I9*(1-J9) -> 1986.04 | N9: ="Q"&ROUNDUP(MONTH(B9)/3,0) -> Q1 | O9: =(L9/K9)*100 -> 9.9857002 | P9: =VLOOKUP(retail_sales_2023!C9,customers!A:J,5,) -> Patna | Q9: =VLOOKUP(C9,customers!A:J,10,0) -> Premium
A10: ORD000840 | B10: 45104 | C10: CUST0113 | D10: Harita Chaudhari | E10: North | F10: Sports | G10: Gym Gloves | H10: 2 | I10: 4112.32 | J10: 0.15 | K10: 6990.94 | L10: 1727.97 | M10: =H10*I10*(1-J10) -> 6990.944 | N10: ="Q"&ROUNDUP(MONTH(B10)/3,0) -> Q2 | O10: =(L10/K10)*100 -> 24.717277 | P10: =VLOOKUP(retail_sales_2023!C10,customers!A:J,5,) -> Lucknow | Q10: =VLOOKUP(C10,customers!A:J,10,0) -> Premium
A11: ORD003889 | B11: 45061 | C11: CUST0306 | D11: Aahana Agarwal | E11: West | F11: Sports | G11: Jump Rope | H11: 1 | I11: 5036.18 | J11: 0 | K11: 5036.18 | L11: 829.34 | M11: =H11*I11*(1-J11) -> 5036.18 | N11: ="Q"&ROUNDUP(MONTH(B11)/3,0) -> Q2 | O11: =(L11/K11)*100 -> 16.46764 | P11: =VLOOKUP(retail_sales_2023!C11,customers!A:J,5,) -> Nagpur | Q11: =VLOOKUP(C11,customers!A:J,10,0) -> Premium
A12: ORD007133 | B12: 45044 | C12: CUST0020 | D12: Neelima Menon | E12: East | F12: Toys | G12: Action Figure Pack | H12: 2 | I12: 3890.76 | J12: 0 | K12: 7781.52 | L12: 1530.84 | M12: =H12*I12*(1-J12) -> 7781.52 | N12: ="Q"&ROUNDUP(MONTH(B12)/3,0) -> Q2 | O12: =(L12/K12)*100 -> 19.672763 | P12: =VLOOKUP(retail_sales_2023!C12,customers!A:J,5,) -> Guwahati | Q12: =VLOOKUP(C12,customers!A:J,10,0) -> Regular
A13: ORD000527 | B13: 44987 | C13: CUST0134 | D13: Hemang Bhavsar | E13: West | F13: Groceries | G13: Oats 1kg | H13: 1 | I13: 464.5 | J13: 0.3 | K13: 325.15 | L13: 23.12 | M13: =H13*I13*(1-J13) -> 325.15 | N13: ="Q"&ROUNDUP(MONTH(B13)/3,0) -> Q1 | O13: =(L13/K13)*100 -> 7.1105644 | P13: =VLOOKUP(retail_sales_2023!C13,customers!A:J,5,) -> Surat | Q13: =VLOOKUP(C13,customers!A:J,10,0) -> Premium
... A79: ORD009486 | B79: 45168 | C79: CUST0030 | D79: Kashvi Sahota | E79: North | F79: Toys | G79: Building Blocks | H79: 2 | I79: 3097.62 | J79: 0 | K79: 6195.24 | L79: 2070.72 | M79: =H79*I79*(1-J79) -> 6195.24 | N79: ="Q"&ROUNDUP(MONTH(B79)/3,0) -> Q3 | O79: =(L79/K79)*100 -> 33.424371 | P79: =VLOOKUP(retail_sales_2023!C79,customers!A:J,5,) -> Delhi | Q79: =VLOOKUP(C79,customers!A:J,10,0) -> Premium
A80: ORD002385 | B80: 44986 | C80: CUST0285 | D80: Mitesh Padmanabhan | E80: West | F80: Clothing | G80: Casual Shorts | H80: 0 | I80: 2549.72 | J80: 0 | K80: 0 | L80: 0 | M80: =H80*I80*(1-J80) -> 0 | N80: ="Q"&ROUNDUP(MONTH(B80)/3,0) -> Q1 | O80: 0 | P80: =VLOOKUP(retail_sales_2023!C80,customers!A:J,5,) -> Pune | Q80: =VLOOKUP(C80,customers!A:J,10,0) -> Premium
A81: ORD010947 | B81: 45282 | C81: CUST0477 | D81: Teerth Bobal | E81: East | F81: Books | G81: Machine Learning A-Z | H81: 1 | I81: 757.58 | J81: 0 | K81: 757.58 | L81: 236.9 | M81: =H81*I81*(1-J81) -> 757.58 | N81: ="Q"&ROUNDUP(MONTH(B81)/3,0) -> Q4 | O81: =(L81/K81)*100 -> 31.270625 | P81: =VLOOKUP(retail_sales_2023!C81,customers!A:J,5,) -> Patna | Q81: =VLOOKUP(C81,customers!A:J,10,0) -> Occasional
A82: ORD002706 | B82: 45037 | C82: CUST0023 | D82: Udyati Dâ€™Alia | E82: West | F82: Electronics | G82: Tablet Pro | H82: 5 | I82: 12177.73 | J82: 0.1 | K82: 54799.78 | L82: 5120.14 | M82: =H82*I82*(1-J82) -> 54799.785 | N82: ="Q"&ROUNDUP(MONTH(B82)/3,0) -> Q2 | O82: =(L82/K82)*100 -> 9.3433587 | P82: =VLOOKUP(retail_sales_2023!C82,customers!A:J,5,) -> Mumbai | Q82: =VLOOKUP(C82,customers!A:J,10,0) -> Regular
A83: ORD006451 | B83: 44933 | C83: CUST0477 | D83: Teerth Bobal | E83: East | F83: Electronics | G83: Smartphone X12 | H83: 5 | I83: 33411.97 | J83: 0.1 | K83: 150353.87 | L83: 21925.55 | M83: =H83*I83*(1-J83) -> 150353.87 | N83: ="Q"&ROUNDUP(MONTH(B83)/3,0) -> Q1 | O83: =(L83/K83)*100 -> 14.582631 | P83: =VLOOKUP(retail_sales_2023!C83,customers!A:J,5,) -> Patna | Q83: =VLOOKUP(C83,customers!A:J,10,0) -> Occasional
A84: ORD008860 | B84: 45235 | C84: CUST0429 | D84: Daniel Rau | E84: North | F84: Books | G84: Leadership 101 | H84: 4 | I84: 845.82 | J84: 0.05 | K84: 3214.12 | L84: 1389.1 | M84: =H84*I84*(1-J84) -> 3214.116 | N84: ="Q"&ROUNDUP(MONTH(B84)/3,0) -> Q4 | O84: =(L84/K84)*100 -> 43.218673 | P84: =VLOOKUP(retail_sales_2023!C84,customers!A:J,5,) -> Jaipur | Q84: =VLOOKUP(C84,customers!A:J,10,0) -> Premium
A85: ORD011405 | B85: 44988 | C85: CUST0127 | D85: Upma Sanghvi | E85: East | F85: Electronics | G85: Laptop 15" | H85: 5 | I85: 37707.69 | J85: 0.25 | K85: 141403.84 | L85: 15241.73 | M85: =H85*I85*(1-J85) -> 141403.84 | N85: ="Q"&ROUNDUP(MONTH(B85)/3,0) -> Q1 | O85: =(L85/K85)*100 -> 10.778866 | P85: =VLOOKUP(retail_sales_2023!C85,customers!A:J,5,) -> Patna | Q85: =VLOOKUP(C85,customers!A:J,10,0) -> Occasional
A86: ORD001746 | B86: 44974 | C86: CUST0047 | D86: Chameli Dani | E86: East | F86: Electronics | G86: Wireless Headphones | H86: 1 | I86: 35714.08 | J86: 0 | K86: 35714.08 | L86: 4936.18 | M86: =H86*I86*(1-J86) -> 35714.08 | N86: ="Q"&ROUNDUP(MONTH(B86)/3,0) -> Q1 | O86: =(L86/K86)*100 -> 13.821384 | P86: =VLOOKUP(retail_sales_2023!C86,customers!A:J,5,) -> Patna | Q86: =VLOOKUP(C86,customers!A:J,10,0) -> Regular
A87: ORD010292 | B87: 45018 | C87: CUST0263 | D87: Jacob Radhakrishnan | E87: East | F87: Furniture | G87: 3-Seater Sofa | H87: 2 | I87: 7624.45 | J87: 0 | K87: 15248.9 | L87: 3176.57 | M87: =H87*I87*(1-J87) -> 15248.9 | N87: ="Q"&ROUNDUP(MONTH(B87)/3,0) -> Q2 | O87: =(L87/K87)*100 -> 20.83147 | P87: =VLOOKUP(retail_sales_2023!C87,customers!A:J,5,) -> Kolkata | Q87: =VLOOKUP(C87,customers!A:J,10,0) -> Premium
A88: ORD006710 | B88: 45176 | C88: CUST0454 | D88: Avi Kar | E88: East | F88: Books | G88: Python Programming | H88: 2 | I88: 398.96 | J88: 0 | K88: 797.92 | L88: 250.02 | M88: =H88*I88*(1-J88) -> 797.92 | N88: ="Q"&ROUNDUP(MONTH(B88)/3,0) -> Q3 | O88: =(L88/K88)*100 -> 31.333968 | P88: =VLOOKUP(retail_sales_2023!C88,customers!A:J,5,) -> Patna | Q88: =VLOOKUP(C88,customers!A:J,10,0) -> Regular
A89: ORD011951 | B89: 44956 | C89: CUST0215 | D89: Kamya Apte | E89: West | F89: Electronics | G89: Smartwatch | H89: 4 | I89: 3635.76 | J89: 0 | K89: 14543.04 | L89: 2229.38 | M89: =H89*I89*(1-J89) -> 14543.04 | N89: ="Q"&ROUNDUP(MONTH(B89)/3,0) -> Q1 | O89: =(L89/K89)*100 -> 15.329532 | P89: =VLOOKUP(retail_sales_2023!C89,customers!A:J,5,) -> Surat | Q89: =VLOOKUP(C89,customers!A:J,10,0) -> Premium
A90: ORD002699 | B90: 45203 | C90: CUST0410 | D90: Matthew Sule | E90: North | F90: Books | G90: Digital Marketing | H90: 5 | I90: 553.03 | J90: 0.05 | K90: 2626.89 | L90: 1182.36 | M90: =H90*I90*(1-J90) -> 2626.8925 | N90: ="Q"&ROUNDUP(MONTH(B90)/3,0) -> Q4 | O90: =(L90/K90)*100 -> 45.009879 | P90: =VLOOKUP(retail_sales_2023!C90,customers!A:J,5,) -> Amritsar | Q90: =VLOOKUP(C90,customers!A:J,10,0) -> Premium
A91: ORD001424 | B91: 45116 | C91: CUST0469 | D91: Brinda Doshi | E91: South | F91: Sports | G91: Resistance Bands | H91: 3 | I91: 3137.33 | J91: 0.1 | K91: 8470.79 | L91: 2061.56 | M91: =H91*I91*(1-J91) -> 8470.791 | N91: ="Q"&ROUNDUP(MONTH(B91)/3,0) -> Q3 | O91: =(L91/K91)*100 -> 24.337281 | P91: =VLOOKUP(retail_sales_2023!C91,customers!A:J,5,) -> Kochi | Q91: =VLOOKUP(C91,customers!A:J,10,0) -> Regular
A92: ORD001062 | B92: 45149 | C92: CUST0052 | D92: Vivaan Parmer | E92: East | F92: Sports | G92: Resistance Bands | H92: 4 | I92: 2168.37 | J92: 0 | K92: 8673.48 | L92: 1454.75 | M92: =H92*I92*(1-J92) -> 8673.48 | N92: ="Q"&ROUNDUP(MONTH(B92)/3,0) -> Q3 | O92: =(L92/K92)*100 -> 16.772391 | P92: =VLOOKUP(retail_sales_2023!C92,customers!A:J,5,) -> Bhubaneswar | Q92: =VLOOKUP(C92,customers!A:J,10,0) -> Occasional
... A225: ORD009696 | B225: 45247 | C225: CUST0161 | D225: Jalsa Narang | E225: North | F225: Groceries | G225: Mixed Nuts 500g | H225: 6 | I225: 545.81 | J225: 0 | K225: 3274.86 | L225: 259.86 | M225: =H225*I225*(1-J225) -> 3274.86 | N225: ="Q"&ROUNDUP(MONTH(B225)/3,0) -> Q4 | O225: =(L225/K225)*100 -> 7.9349957 | P225: =VLOOKUP(retail_sales_2023!C225,customers!A:J,5,) -> Lucknow | Q225: =VLOOKUP(C225,customers!A:J,10,0) -> Premium
A226: ORD008293 | B226: 45077 | C226: CUST0223 | D226: Aarini Dugar | E226: East | F226: Electronics | G226: Tablet Pro | H226: 0 | I226: 40088 | J226: 0.15 | K226: 0 | L226: 0 | M226: =H226*I226*(1-J226) -> 0 | N226: ="Q"&ROUNDUP(MONTH(B226)/3,0) -> Q2 | O226: 0 | P226: =VLOOKUP(retail_sales_2023!C226,customers!A:J,5,) -> Guwahati | Q226: =VLOOKUP(C226,customers!A:J,10,0) -> Premium
A227: ORD007075 | B227: 45069 | C227: CUST0317 | D227: Balendra Soman | E227: West | F227: Clothing | G227: Men Formal Shirt | H227: 1 | I227: 1055.81 | J227: 0.25 | K227: 791.86 | L227: 177.36 | M227: =H227*I227*(1-J227) -> 791.8575 | N227: ="Q"&ROUNDUP(MONTH(B227)/3,0) -> Q2 | O227: =(L227/K227)*100 -> 22.397899 | P227: =VLOOKUP(retail_sales_2023!C227,customers!A:J,5,) -> Nagpur | Q227: =VLOOKUP(C227,customers!A:J,10,0) -> Occasional
A228: ORD002009 | B228: 45251 | C228: CUST0300 | D228: Maanav Kashyap | E228: North | F228: Sports | G228: Cycling Helmet | H228: 4 | I228: 5959.73 | J228: 0.2 | K228: 19071.14 | L228: 4403.71 | M228: =H228*I228*(1-J228) -> 19071.136 | N228: ="Q"&ROUNDUP(MONTH(B228)/3,0) -> Q4 | O228: =(L228/K228)*100 -> 23.090964 | P228: =VLOOKUP(retail_sales_2023!C228,customers!A:J,5,) -> Amritsar | Q228: =VLOOKUP(C228,customers!A:J,10,0) -> Premium
A229: ORD006553 | B229: 45165 | C229: CUST0095 | D229: Pahal Goyal | E229: North | F229: Sports | G229: Cricket Bat | H229: 4 | I229: 2576.2 | J229: 0.1 | K229: 9274.32 | L229: 2328.5 | M229: =H229*I229*(1-J229) -> 9274.32 | N229: ="Q"&ROUNDUP(MONTH(B229)/3,0) -> Q3 | O229: =(L229/K229)*100 -> 25.106962 | P229: =VLOOKUP(retail_sales_2023!C229,customers!A:J,5,) -> Jaipur | Q229: =VLOOKUP(C229,customers!A:J,10,0) -> Premium
A230: ORD010185 | B230: 45001 | C230: CUST0454 | D230: Avi Kar | E230: East | F230: Groceries | G230: Organic Honey 500g | H230: 1 | I230: 733.4 | J230: 0.2 | K230: 586.72 | L230: 45.87 | M230: =H230*I230*(1-J230) -> 586.72 | N230: ="Q"&ROUNDUP(MONTH(B230)/3,0) -> Q1 | O230: =(L230/K230)*100 -> 7.8180393 | P230: =VLOOKUP(retail_sales_2023!C230,customers!A:J,5,) -> Patna | Q230: =VLOOKUP(C230,customers!A:J,10,0) -> Regular
A231: ORD002645 | B231: 45115 | C231: CUST0495 | D231: Chanchal Golla | E231: North | F231: Sports | G231: Running Shoes | H231: 5 | I231: 3306.85 | J231: 0 | K231: 16534.25 | L231: 4455.44 | M231: =H231*I231*(1-J231) -> 16534.25 | N231: ="Q"&ROUNDUP(MONTH(B231)/3,0) -> Q3 | O231: =(L231/K231)*100 -> 26.946732 | P231: =VLOOKUP(retail_sales_2023!C231,customers!A:J,5,) -> Amritsar | Q231: =VLOOKUP(C231,customers!A:J,10,0) -> Premium
A232: ORD007274 | B232: 45181 | C232: CUST0019 | D232: Saksham Pillay | E232: West | F232: Furniture | G232: Shoe Rack | H232: 3 | I232: 19095.49 | J232: 0.1 | K232: 51557.82 | L232: 13308.76 | M232: =H232*I232*(1-J232) -> 51557.823 | N232: ="Q"&ROUNDUP(MONTH(B232)/3,0) -> Q3 | O232: =(L232/K232)*100 -> 25.813271 | P232: =VLOOKUP(retail_sales_2023!C232,customers!A:J,5,) -> Surat | Q232: =VLOOKUP(C232,customers!A:J,10,0) -> Regular
A233: ORD004885 | B233: 44931 | C233: CUST0287 | D233: Harish Sahota | E233: North | F233: Toys | G233: Barbie Doll Set | H233: 4 | I233: 2382.14 | J233: 0.15 | K233: 8099.28 | L233: 2620.28 | M233: =H233*I233*(1-J233) -> 8099.276 | N233: ="Q"&ROUNDUP(MONTH(B233)/3,0) -> Q1 | O233: =(L233/K233)*100 -> 32.352012 | P233: =VLOOKUP(retail_sales_2023!C233,customers!A:J,5,) -> Delhi | Q233: =VLOOKUP(C233,customers!A:J,10,0) -> Regular
A234: ORD011157 | B234: 45110 | C234: CUST0433 | D234: Oliver Ram | E234: South | F234: Groceries | G234: Sunflower Oil 1L | H234: 3 | I234: 456.13 | J234: 0.1 | K234: 1231.55 | L234: 73.52 | M234: =H234*I234*(1-J234) -> 1231.551 | N234: ="Q"&ROUNDUP(MONTH(B234)/3,0) -> Q3 | O234: =(L234/K234)*100 -> 5.969713 | P234: =VLOOKUP(retail_sales_2023!C234,customers!A:J,5,) -> Kochi | Q234: =VLOOKUP(C234,customers!A:J,10,0) -> Premium
A235: ORD008010 | B235: 45063 | C235: CUST0269 | D235: Fiyaz Verma | E235: West | F235: Groceries | G235: Instant Coffee 200g | H235: 2 | I235: 112.94 | J235: 0.05 | K235: 214.59 | L235: 19.02 | M235: =H235*I235*(1-J235) -> 214.586 | N235: ="Q"&ROUNDUP(MONTH(B235)/3,0) -> Q2 | O235: =(L235/K235)*100 -> 8.863414 | P235: =VLOOKUP(retail_sales_2023!C235,customers!A:J,5,) -> Mumbai | Q235: =VLOOKUP(C235,customers!A:J,10,0) -> Premium
A236: ORD010975 | B236: 45115 | C236: CUST0250 | D236: Vanya Subramaniam | E236: West | F236: Furniture | G236: 3-Seater Sofa | H236: 1 | I236: 2843.84 | J236: 0.15 | K236: 2417.26 | L236: 689.21 | M236: =H236*I236*(1-J236) -> 2417.264 | N236: ="Q"&ROUNDUP(MONTH(B236)/3,0) -> Q3 | O236: =(L236/K236)*100 -> 28.512034 | P236: =VLOOKUP(retail_sales_2023!C236,customers!A:J,5,) -> Surat | Q236: =VLOOKUP(C236,customers!A:J,10,0) -> Premium
A237: ORD002138 | B237: 45251 | C237: CUST0242 | D237: Vanya Bhat | E237: North | F237: Groceries | G237: Organic Honey 500g | H237: 9 | I237: 344.46 | J237: 0.25 | K237: 2325.11 | L237: 161.86 | M237: =H237*I237*(1-J237) -> 2325.105 | N237: ="Q"&ROUNDUP(MONTH(B237)/3,0) -> Q4 | O237: =(L237/K237)*100 -> 6.9613911 | P237: =VLOOKUP(retail_sales_2023!C237,customers!A:J,5,) -> Delhi | Q237: =VLOOKUP(C237,customers!A:J,10,0) -> Regular
A238: ORD001127 | B238: 45090 | C238: CUST0251 | D238: Faris Thakkar | E238: South | F238: Clothing | G238: Women Kurti | H238: 1 | I238: 4591.78 | J238: 0.15 | K238: 3903.01 | L238: 1448.98 | M238: =H238*I238*(1-J238) -> 3903.013 | N238: ="Q"&ROUNDUP(MONTH(B238)/3,0) -> Q2 | O238: =(L238/K238)*100 -> 37.124681 | P238: =VLOOKUP(retail_sales_2023!C238,customers!A:J,5,) -> Kochi | Q238: =VLOOKUP(C238,customers!A:J,10,0) -> Regular
... A282: ORD000438 | B282: 45126 | C282: CUST0326 | D282: Ekantika Bhatnagar | E282: West | F282: Sports | G282: Yoga Mat | H282: 4 | I282: 5388.45 | J282: 0.05 | K282: 20476.11 | L282: 4361.93 | M282: =H282*I282*(1-J282) -> 20476.11 | N282: ="Q"&ROUNDUP(MONTH(B282)/3,0) -> Q3 | O282: =(L282/K282)*100 -> 21.302533 | P282: =VLOOKUP(retail_sales_2023!C282,customers!A:J,5,) -> Pune | Q282: =VLOOKUP(C282,customers!A:J,10,0) -> Premium
A283: ORD006174 | B283: 45070 | C283: CUST0188 | D283: Anusha Pathak | E283: South | F283: Sports | G283: Jump Rope | H283: 0 | I283: 6318.52 | J283: 0.05 | K283: 0 | L283: 0 | M283: =H283*I283*(1-J283) -> 0 | N283: ="Q"&ROUNDUP(MONTH(B283)/3,0) -> Q2 | O283: 0 | P283: =VLOOKUP(retail_sales_2023!C283,customers!A:J,5,) -> Chennai | Q283: =VLOOKUP(C283,customers!A:J,10,0) -> Regular
A284: ORD008239 | B284: 45085 | C284: CUST0248 | D284: Noah Varkey | E284: South | F284: Electronics | G284: 4K Smart TV | H284: 5 | I284: 14581.09 | J284: 0 | K284: 72905.45 | L284: 8145.79 | M284: =H284*I284*(1-J284) -> 72905.45 | N284: ="Q"&ROUNDUP(MONTH(B284)/3,0) -> Q2 | O284: =(L284/K284)*100 -> 11.173088 | P284: =VLOOKUP(retail_sales_2023!C284,customers!A:J,5,) -> Kochi | Q284: =VLOOKUP(C284,customers!A:J,10,0) -> Occasional
A285: ORD004007 | B285: 44938 | C285: CUST0022 | D285: Jagdish Wali | E285: South | F285: Sports | G285: Jump Rope | H285: 5 | I285: 5659.07 | J285: 0.05 | K285: 26880.58 | L285: 4360.01 | M285: =H285*I285*(1-J285) -> 26880.582 | N285: ="Q"&ROUNDUP(MONTH(B285)/3,0) -> Q1 | O285: =(L285/K285)*100 -> 16.219925 | P285: =VLOOKUP(retail_sales_2023!C285,customers!A:J,5,) -> Coimbatore | Q285: =VLOOKUP(C285,customers!A:J,10,0) -> Premium
A286: ORD004240 | B286: 45212 | C286: CUST0313 | D286: Nikita Kala | E286: South | F286: Clothing | G286: Men Formal Shirt | H286: 1 | I286: 1474.01 | J286: 0.05 | K286: 1400.31 | L286: 313.33 | M286: =H286*I286*(1-J286) -> 1400.3095 | N286: ="Q"&ROUNDUP(MONTH(B286)/3,0) -> Q4 | O286: =(L286/K286)*100 -> 22.37576 | P286: =VLOOKUP(retail_sales_2023!C286,customers!A:J,5,) -> Coimbatore | Q286: =VLOOKUP(C286,customers!A:J,10,0) -> Regular
A287: ORD006868 | B287: 45097 | C287: CUST0410 | D287: Matthew Sule | E287: North | F287: Groceries | G287: Whole Wheat Flour 5kg | H287: 1 | I287: 176.36 | J287: 0.25 | K287: 132.27 | L287: 7.46 | M287: =H287*I287*(1-J287) -> 132.27 | N287: ="Q"&ROUNDUP(MONTH(B287)/3,0) -> Q2 | O287: =(L287/K287)*100 -> 5.6399788 | P287: =VLOOKUP(retail_sales_2023!C287,customers!A:J,5,) -> Amritsar | Q287: =VLOOKUP(C287,customers!A:J,10,0) -> Premium
A288: ORD004969 | B288: 44965 | C288: CUST0173 | D288: Wahab Kothari | E288: West | F288: Sports | G288: Table Tennis Set | H288: 2 | I288: 1910.16 | J288: 0.1 | K288: 3438.29 | L288: 788.49 | M288: =H288*I288*(1-J288) -> 3438.288 | N288: ="Q"&ROUNDUP(MONTH(B288)/3,0) -> Q1 | O288: =(L288/K288)*100 -> 22.932621 | P288: =VLOOKUP(retail_sales_2023!C288,customers!A:J,5,) -> Mumbai | Q288: =VLOOKUP(C288,customers!A:J,10,0) -> Premium
A289: ORD000963 | B289: 45110 | C289: CUST0005 | D289: Mason Dutt | E289: South | F289: Electronics | G289: USB-C Hub | H289: 1 | I289: 29781.14 | J289: 0 | K289: 29781.14 | L289: 3502.64 | M289: =H289*I289*(1-J289) -> 29781.14 | N289: ="Q"&ROUNDUP(MONTH(B289)/3,0) -> Q3 | O289: =(L289/K289)*100 -> 11.761269 | P289: =VLOOKUP(retail_sales_2023!C289,customers!A:J,5,) -> Coimbatore | Q289: =VLOOKUP(C289,customers!A:J,10,0) -> Regular
A290: ORD001836 | B290: 45228 | C290: CUST0326 | D290: Ekantika Bhatnagar | E290: West | F290: Furniture | G290: Bookshelf 5-Tier | H290: 5 | I290: 20954.16 | J290: 0.05 | K290: 99532.26 | L290: 30568.53 | M290: =H290*I290*(1-J290) -> 99532.26 | N290: ="Q"&ROUNDUP(MONTH(B290)/3,0) -> Q4 | O290: =(L290/K290)*100 -> 30.712183 | P290: =VLOOKUP(retail_sales_2023!C290,customers!A:J,5,) -> Pune | Q290: =VLOOKUP(C290,customers!A:J,10,0) -> Premium
A291: ORD007368 | B291: 45119 | C291: CUST0388 | D291: Ekavir Chawla | E291: West | F291: Sports | G291: Running Shoes | H291: 2 | I291: 4198.86 | J291: 0.1 | K291: 7557.95 | L291: 2059.61 | M291: =H291*I291*(1-J291) -> 7557.948 | N291: ="Q"&ROUNDUP(MONTH(B291)/3,0) -> Q3 | O291: =(L291/K291)*100 -> 27.250908 | P291: =VLOOKUP(retail_sales_2023!C291,customers!A:J,5,) -> Ahmedabad | Q291: =VLOOKUP(C291,customers!A:J,10,0) -> Premium
A292: ORD006845 | B292: 45048 | C292: CUST0083 | D292: Tanmayi Pant | E292: East | F292: Clothing | G292: Men Formal Shirt | H292: 5 | I292: 3746.4 | J292: 0.15 | K292: 15922.2 | L292: 5571.7 | M292: =H292*I292*(1-J292) -> 15922.2 | N292: ="Q"&ROUNDUP(MONTH(B292)/3,0) -> Q2 | O292: =(L292/K292)*100 -> 34.99328 | P292: =VLOOKUP(retail_sales_2023!C292,customers!A:J,5,) -> Ranchi | Q292: =VLOOKUP(C292,customers!A:J,10,0) -> Premium
A293: ORD009654 | B293: 45083 | C293: CUST0373 | D293: Ikbal Randhawa | E293: East | F293: Electronics | G293: Tablet Pro | H293: 5 | I293: 39346.32 | J293: 0 | K293: 196731.6 | L293: 30429.46 | M293: =H293*I293*(1-J293) -> 196731.6 | N293: ="Q"&ROUNDUP(MONTH(B293)/3,0) -> Q2 | O293: =(L293/K293)*100 -> 15.4675 | P293: =VLOOKUP(retail_sales_2023!C293,customers!A:J,5,) -> Patna | Q293: =VLOOKUP(C293,customers!A:J,10,0) -> Premium
A294: ORD004127 | B294: 45264 | C294: CUST0416 | D294: Hitesh Soman | E294: West | F294: Electronics | G294: Bluetooth Speaker | H294: 2 | I294: 3122.2 | J294: 0.1 | K294: 5619.96 | L294: 585.74 | M294: =H294*I294*(1-J294) -> 5619.96 | N294: ="Q"&ROUNDUP(MONTH(B294)/3,0) -> Q4 | O294: =(L294/K294)*100 -> 10.422494 | P294: =VLOOKUP(retail_sales_2023!C294,customers!A:J,5,) -> Mumbai | Q294: =VLOOKUP(C294,customers!A:J,10,0) -> Premium
A295: ORD004911 | B295: 45038 | C295: CUST0240 | D295: Suhani Shanker | E295: South | F295: Clothing | G295: Sports T-Shirt | H295: 4 | I295: 4589.53 | J295: 0.1 | K295: 16522.31 | L295: 5771.53 | M295: =H295*I295*(1-J295) -> 16522.308 | N295: ="Q"&ROUNDUP(MONTH(B295)/3,0) -> Q2 | O295: =(L295/K295)*100 -> 34.931738 | P295: =VLOOKUP(retail_sales_2023!C295,customers!A:J,5,) -> Kochi | Q295: =VLOOKUP(C295,customers!A:J,10,0) -> Regular
... A856: ORD011085 | B856: 45217 | C856: CUST0062 | D856: Veer Tandon | E856: South | F856: Electronics | G856: Smartphone X12 | H856: 1 | I856: 64961.59 | J856: 0.25 | K856: 48721.19 | L856: 5214.12 | M856: =H856*I856*(1-J856) -> 48721.192 | N856: ="Q"&ROUNDUP(MONTH(B856)/3,0) -> Q4 | O856: =(L856/K856)*100 -> 10.701955 | P856: =VLOOKUP(retail_sales_2023!C856,customers!A:J,5,) -> Coimbatore | Q856: =VLOOKUP(C856,customers!A:J,10,0) -> Regular
A857: ORD008672 | B857: 45244 | C857: CUST0492 | D857: Pranav Gala | E857: South | F857: Sports | G857: Badminton Racket | H857: 0 | I857: 3761.59 | J857: 0.25 | K857: 0 | L857: 0 | M857: =H857*I857*(1-J857) -> 0 | N857: ="Q"&ROUNDUP(MONTH(B857)/3,0) -> Q4 | O857: 0 | P857: =VLOOKUP(retail_sales_2023!C857,customers!A:J,5,) -> Coimbatore | Q857: =VLOOKUP(C857,customers!A:J,10,0) -> Premium
A858: ORD011816 | B858: 45045 | C858: CUST0034 | D858: Bachittar Sarma | E858: East | F858: Groceries | G858: Turmeric Powder 200g | H858: 10 | I858: 505.58 | J858: 0.2 | K858: 4044.64 | L858: 243.3 | M858: =H858*I858*(1-J858) -> 4044.64 | N858: ="Q"&ROUNDUP(MONTH(B858)/3,0) -> Q2 | O858: =(L858/K858)*100 -> 6.0153685 | P858: =VLOOKUP(retail_sales_2023!C858,customers!A:J,5,) -> Bhubaneswar | Q858: =VLOOKUP(C858,customers!A:J,10,0) -> Occasional
A859: ORD008902 | B859: 45018 | C859: CUST0036 | D859: Amaira Venkataraman | E859: North | F859: Sports | G859: Football | H859: 3 | I859: 5270.12 | J859: 0.05 | K859: 15019.84 | L859: 3700.46 | M859: =H859*I859*(1-J859) -> 15019.842 | N859: ="Q"&ROUNDUP(MONTH(B859)/3,0) -> Q2 | O859: =(L859/K859)*100 -> 24.637147 | P859: =VLOOKUP(retail_sales_2023!C859,customers!A:J,5,) -> Amritsar | Q859: =VLOOKUP(C859,customers!A:J,10,0) -> Premium
A860: ORD007063 | B860: 45171 | C860: CUST0280 | D860: Chandani Narayanan | E860: East | F860: Groceries | G860: Mixed Nuts 500g | H860: 10 | I860: 116.73 | J860: 0.05 | K860: 1108.93 | L860: 88.29 | M860: =H860*I860*(1-J860) -> 1108.935 | N860: ="Q"&ROUNDUP(MONTH(B860)/3,0) -> Q3 | O860: =(L860/K860)*100 -> 7.9617289 | P860: =VLOOKUP(retail_sales_2023!C860,customers!A:J,5,) -> Patna | Q860: =VLOOKUP(C860,customers!A:J,10,0) -> Regular
A861: ORD003885 | B861: 44999 | C861: CUST0336 | D861: Krishna Saxena | E861: West | F861: Clothing | G861: Salwar Kameez | H861: 1 | I861: 1949.39 | J861: 0 | K861: 1949.39 | L861: 671.3 | M861: =H861*I861*(1-J861) -> 1949.39 | N861: ="Q"&ROUNDUP(MONTH(B861)/3,0) -> Q1 | O861: =(L861/K861)*100 -> 34.436413 | P861: =VLOOKUP(retail_sales_2023!C861,customers!A:J,5,) -> Ahmedabad | Q861: =VLOOKUP(C861,customers!A:J,10,0) -> Premium
A862: ORD003276 | B862: 44961 | C862: CUST0468 | D862: Mason Bahl | E862: North | F862: Electronics | G862: Smartwatch | H862: 3 | I862: 57238.94 | J862: 0.1 | K862: 154545.14 | L862: 23742.02 | M862: =H862*I862*(1-J862) -> 154545.14 | N862: ="Q"&ROUNDUP(MONTH(B862)/3,0) -> Q1 | O862: =(L862/K862)*100 -> 15.362515 | P862: =VLOOKUP(retail_sales_2023!C862,customers!A:J,5,) -> Chandigarh | Q862: =VLOOKUP(C862,customers!A:J,10,0) -> Regular
A863: ORD003140 | B863: 44997 | C863: CUST0403 | D863: Bimala Rattan | E863: East | F863: Electronics | G863: Laptop 15" | H863: 3 | I863: 13890.26 | J863: 0 | K863: 41670.78 | L863: 4768.23 | M863: =H863*I863*(1-J863) -> 41670.78 | N863: ="Q"&ROUNDUP(MONTH(B863)/3,0) -> Q1 | O863: =(L863/K863)*100 -> 11.442622 | P863: =VLOOKUP(retail_sales_2023!C863,customers!A:J,5,) -> Bhubaneswar | Q863: =VLOOKUP(C863,customers!A:J,10,0) -> Regular
A864: ORD008633 | B864: 45125 | C864: CUST0203 | D864: Yagnesh Deo | E864: South | F864: Sports | G864: Yoga Mat | H864: 4 | I864: 7946.33 | J864: 0.05 | K864: 30196.05 | L864: 7729.41 | M864: =H864*I864*(1-J864) -> 30196.054 | N864: ="Q"&ROUNDUP(MONTH(B864)/3,0) -> Q3 | O864: =(L864/K864)*100 -> 25.597421 | P864: =VLOOKUP(retail_sales_2023!C864,customers!A:J,5,) -> Lucknow | Q864: =VLOOKUP(C864,customers!A:J,10,0) -> Premium
A865: ORD003193 | B865: 45166 | C865: CUST0396 | D865: Ojasvi Krishnan | E865: West | F865: Electronics | G865: Smartwatch | H865: 4 | I865: 47006.04 | J865: 0.1 | K865: 169221.74 | L865: 19456.24 | M865: =H865*I865*(1-J865) -> 169221.74 | N865: ="Q"&ROUNDUP(MONTH(B865)/3,0) -> Q3 | O865: =(L865/K865)*100 -> 11.497483 | P865: =VLOOKUP(retail_sales_2023!C865,customers!A:J,5,) -> Pune | Q865: =VLOOKUP(C865,customers!A:J,10,0) -> Premium
A866: ORD001330 | B866: 44948 | C866: CUST0479 | D866: Janya Walia | E866: West | F866: Electronics | G866: Tablet Pro | H866: 5 | I866: 12794.35 | J866: 0.05 | K866: 60773.16 | L866: 7863.71 | M866: =H866*I866*(1-J866) -> 60773.162 | N866: ="Q"&ROUNDUP(MONTH(B866)/3,0) -> Q1 | O866: =(L866/K866)*100 -> 12.939446 | P866: =VLOOKUP(retail_sales_2023!C866,customers!A:J,5,) -> Pune | Q866: =VLOOKUP(C866,customers!A:J,10,0) -> Premium
A867: ORD002463 | B867: 45211 | C867: CUST0086 | D867: Sara Chandran | E867: East | F867: Furniture | G867: Wardrobe 3-Door | H867: 1 | I867: 16750.79 | J867: 0.15 | K867: 14238.17 | L867: -1116.95 | M867: =H867*I867*(1-J867) -> 14238.172 | N867: ="Q"&ROUNDUP(MONTH(B867)/3,0) -> Q4 | O867: =(L867/K867)*100 -> -7.8447581 | P867: =VLOOKUP(retail_sales_2023!C867,customers!A:J,5,) -> Patna | Q867: =VLOOKUP(C867,customers!A:J,10,0) -> Regular
A868: ORD004340 | B868: 45271 | C868: CUST0131 | D868: Aarna Mukherjee | E868: South | F868: Groceries | G868: Toor Dal 1kg | H868: 5 | I868: 539.9 | J868: 0 | K868: 2699.5 | L868: 238.55 | M868: =H868*I868*(1-J868) -> 2699.5 | N868: ="Q"&ROUNDUP(MONTH(B868)/3,0) -> Q4 | O868: =(L868/K868)*100 -> 8.8368216 | P868: =VLOOKUP(retail_sales_2023!C868,customers!A:J,5,) -> Coimbatore | Q868: =VLOOKUP(C868,customers!A:J,10,0) -> Regular
A869: ORD004706 | B869: 45221 | C869: CUST0357 | D869: Udant Mishra | E869: North | F869: Clothing | G869: Men Formal Shirt | H869: 2 | I869: 3846.74 | J869: 0 | K869: 7693.48 | L869: 2002.39 | M869: =H869*I869*(1-J869) -> 7693.48 | N869: ="Q"&ROUNDUP(MONTH(B869)/3,0) -> Q4 | O869: =(L869/K869)*100 -> 26.027103 | P869: =VLOOKUP(retail_sales_2023!C869,customers!A:J,5,) -> Delhi | Q869: =VLOOKUP(C869,customers!A:J,10,0) -> Premium
... A1143: ORD005537 | B1143: 45067 | C1143: CUST0205 | D1143: Harita Kurian | E1143: South | F1143: Electronics | G1143: DSLR Camera | H1143: 5 | I1143: 30504 | J1143: 0.15 | K1143: 129642 | L1143: 19222.43 | M1143: =H1143*I1143*(1-J1143) -> 129642 | N1143: ="Q"&ROUNDUP(MONTH(B1143)/3,0) -> Q2 | O1143: =(L1143/K1143)*100 -> 14.827317 | P1143: =VLOOKUP(retail_sales_2023!C1143,customers!A:J,5,) -> Hyderabad | Q1143: =VLOOKUP(C1143,customers!A:J,10,0) -> Premium
A1144: ORD008280 | B1144: 45124 | C1144: CUST0078 | D1144: Warinder Naidu | E1144: South | F1144: Groceries | G1144: Green Tea Box | H1144: 0 | I1144: 548.97 | J1144: 0.05 | K1144: 0 | L1144: 0 | M1144: =H1144*I1144*(1-J1144) -> 0 | N1144: ="Q"&ROUNDUP(MONTH(B1144)/3,0) -> Q3 | O1144: 0 | P1144: =VLOOKUP(retail_sales_2023!C1144,customers!A:J,5,) -> Hyderabad | Q1144: =VLOOKUP(C1144,customers!A:J,10,0) -> Regular
A1145: ORD003009 | B1145: 44934 | C1145: CUST0460 | D1145: Zaitra Basak | E1145: South | F1145: Books | G1145: Business Analytics | H1145: 5 | I1145: 297.14 | J1145: 0.15 | K1145: 1262.84 | L1145: 527.44 | M1145: =H1145*I1145*(1-J1145) -> 1262.845 | N1145: ="Q"&ROUNDUP(MONTH(B1145)/3,0) -> Q1 | O1145: =(L1145/K1145)*100 -> 41.766178 | P1145: =VLOOKUP(retail_sales_2023!C1145,customers!A:J,5,) -> Kochi | Q1145: =VLOOKUP(C1145,customers!A:J,10,0) -> Regular
A1146: ORD009642 | B1146: 45038 | C1146: CUST0079 | D1146: Joshua Acharya | E1146: West | F1146: Groceries | G1146: Whole Wheat Flour 5kg | H1146: 5 | I1146: 433.16 | J1146: 0.3 | K1146: 1516.06 | L1146: 150.18 | M1146: =H1146*I1146*(1-J1146) -> 1516.06 | N1146: ="Q"&ROUNDUP(MONTH(B1146)/3,0) -> Q2 | O1146: =(L1146/K1146)*100 -> 9.9059404 | P1146: =VLOOKUP(retail_sales_2023!C1146,customers!A:J,5,) -> Ahmedabad | Q1146: =VLOOKUP(C1146,customers!A:J,10,0) -> Premium
A1147: ORD005138 | B1147: 45117 | C1147: CUST0301 | D1147: Vihaan Saini | E1147: North | F1147: Books | G1147: Power BI Guide | H1147: 5 | I1147: 698.96 | J1147: 0 | K1147: 3494.8 | L1147: 1447.25 | M1147: =H1147*I1147*(1-J1147) -> 3494.8 | N1147: ="Q"&ROUNDUP(MONTH(B1147)/3,0) -> Q3 | O1147: =(L1147/K1147)*100 -> 41.411526 | P1147: =VLOOKUP(retail_sales_2023!C1147,customers!A:J,5,) -> Chandigarh | Q1147: =VLOOKUP(C1147,customers!A:J,10,0) -> Premium
A1148: ORD009093 | B1148: 45196 | C1148: CUST0223 | D1148: Aarini Dugar | E1148: East | F1148: Clothing | G1148: Casual Shorts | H1148: 5 | I1148: 3348.32 | J1148: 0.05 | K1148: 15904.52 | L1148: 3707.09 | M1148: =H1148*I1148*(1-J1148) -> 15904.52 | N1148: ="Q"&ROUNDUP(MONTH(B1148)/3,0) -> Q3 | O1148: =(L1148/K1148)*100 -> 23.308405 | P1148: =VLOOKUP(retail_sales_2023!C1148,customers!A:J,5,) -> Guwahati | Q1148: =VLOOKUP(C1148,customers!A:J,10,0) -> Premium
A1149: ORD008850 | B1149: 45093 | C1149: CUST0248 | D1149: Noah Varkey | E1149: South | F1149: Electronics | G1149: Smartphone X12 | H1149: 1 | I1149: 39998.29 | J1149: 0.1 | K1149: 35998.46 | L1149: 3117.14 | M1149: =H1149*I1149*(1-J1149) -> 35998.461 | N1149: ="Q"&ROUNDUP(MONTH(B1149)/3,0) -> Q2 | O1149: =(L1149/K1149)*100 -> 8.6590926 | P1149: =VLOOKUP(retail_sales_2023!C1149,customers!A:J,5,) -> Kochi | Q1149: =VLOOKUP(C1149,customers!A:J,10,0) -> Occasional
A1150: ORD003328 | B1150: 45181 | C1150: CUST0247 | D1150: Geetika Chopra | E1150: East | F1150: Books | G1150: Power BI Guide | H1150: 4 | I1150: 513.43 | J1150: 0.1 | K1150: 1848.35 | L1150: 558.79 | M1150: =H1150*I1150*(1-J1150) -> 1848.348 | N1150: ="Q"&ROUNDUP(MONTH(B1150)/3,0) -> Q3 | O1150: =(L1150/K1150)*100 -> 30.231828 | P1150: =VLOOKUP(retail_sales_2023!C1150,customers!A:J,5,) -> Kolkata | Q1150: =VLOOKUP(C1150,customers!A:J,10,0) -> Regular
A1151: ORD003944 | B1151: 45139 | C1151: CUST0331 | D1151: Yashvi Manne | E1151: West | F1151: Groceries | G1151: Turmeric Powder 200g | H1151: 6 | I1151: 582.61 | J1151: 0 | K1151: 3495.66 | L1151: 312.23 | M1151: =H1151*I1151*(1-J1151) -> 3495.66 | N1151: ="Q"&ROUNDUP(MONTH(B1151)/3,0) -> Q3 | O1151: =(L1151/K1151)*100 -> 8.9319327 | P1151: =VLOOKUP(retail_sales_2023!C1151,customers!A:J,5,) -> Surat | Q1151: =VLOOKUP(C1151,customers!A:J,10,0) -> Premium
A1152: ORD011169 | B1152: 44974 | C1152: CUST0397 | D1152: Jai Boase | E1152: West | F1152: Groceries | G1152: Turmeric Powder 200g | H1152: 5 | I1152: 764.2 | J1152: 0 | K1152: 3821 | L1152: 267.04 | M1152: =H1152*I1152*(1-J1152) -> 3821 | N1152: ="Q"&ROUNDUP(MONTH(B1152)/3,0) -> Q1 | O1152: =(L1152/K1152)*100 -> 6.9887464 | P1152: =VLOOKUP(retail_sales_2023!C1152,customers!A:J,5,) -> Ahmedabad | Q1152: =VLOOKUP(C1152,customers!A:J,10,0) -> Occasional
A1153: ORD011394 | B1153: 44945 | C1153: CUST0198 | D1153: Dev Wagle | E1153: North | F1153: Clothing | G1153: Men Formal Shirt | H1153: 3 | I1153: 4056.74 | J1153: 0.25 | K1153: 9127.66 | L1153: 2659.97 | M1153: =H1153*I1153*(1-J1153) -> 9127.665 | N1153: ="Q"&ROUNDUP(MONTH(B1153)/3,0) -> Q1 | O1153: =(L1153/K1153)*100 -> 29.141861 | P1153: =VLOOKUP(retail_sales_2023!C1153,customers!A:J,5,) -> Chandigarh | Q1153: =VLOOKUP(C1153,customers!A:J,10,0) -> Regular
A1154: ORD007181 | B1154: 45139 | C1154: CUST0223 | D1154: Unknown | E1154: East | F1154: Sports | G1154: Cycling Helmet | H1154: 3 | I1154: 1274.63 | J1154: 0.15 | K1154: 3250.31 | L1154: 700.83 | M1154: =H1154*I1154*(1-J1154) -> 3250.3065 | N1154: ="Q"&ROUNDUP(MONTH(B1154)/3,0) -> Q3 | O1154: =(L1154/K1154)*100 -> 21.561943 | P1154: =VLOOKUP(retail_sales_2023!C1154,customers!A:J,5,) -> Guwahati | Q1154: =VLOOKUP(C1154,customers!A:J,10,0) -> Premium
A1155: ORD010943 | B1155: 45249 | C1155: CUST0276 | D1155: Manthan Grover | E1155: North | F1155: Toys | G1155: Board Game Monopoly | H1155: 4 | I1155: 3312.11 | J1155: 0 | K1155: 13248.44 | L1155: 3257.71 | M1155: =H1155*I1155*(1-J1155) -> 13248.44 | N1155: ="Q"&ROUNDUP(MONTH(B1155)/3,0) -> Q4 | O1155: =(L1155/K1155)*100 -> 24.589386 | P1155: =VLOOKUP(retail_sales_2023!C1155,customers!A:J,5,) -> Amritsar | Q1155: =VLOOKUP(C1155,customers!A:J,10,0) -> Premium
A1156: ORD010605 | B1156: 45221 | C1156: CUST0470 | D1156: Kabir Tripathi | E1156: West | F1156: Clothing | G1156: Ethnic Saree | H1156: 5 | I1156: 1017.14 | J1156: 0 | K1156: 5085.7 | L1156: 1682.49 | M1156: =H1156*I1156*(1-J1156) -> 5085.7 | N1156: ="Q"&ROUNDUP(MONTH(B1156)/3,0) -> Q4 | O1156: =(L1156/K1156)*100 -> 33.082761 | P1156: =VLOOKUP(retail_sales_2023!C1156,customers!A:J,5,) -> Mumbai | Q1156: =VLOOKUP(C1156,customers!A:J,10,0) -> Occasional
... A1173: ORD007517 | B1173: 44934 | C1173: CUST0373 | D1173: Ikbal Randhawa | E1173: East | F1173: Clothing | G1173: Casual Shorts | H1173: 1 | I1173: 1703.02 | J1173: 0.1 | K1173: 1532.72 | L1173: -36.57 | M1173: =H1173*I1173*(1-J1173) -> 1532.718 | N1173: ="Q"&ROUNDUP(MONTH(B1173)/3,0) -> Q1 | O1173: =(L1173/K1173)*100 -> -2.3859544 | P1173: =VLOOKUP(retail_sales_2023!C1173,customers!A:J,5,) -> Patna | Q1173: =VLOOKUP(C1173,customers!A:J,10,0) -> Premium
A1174: ORD008291 | B1174: 45145 | C1174: CUST0359 | D1174: Yutika Suri | E1174: East | F1174: Groceries | G1174: Mixed Nuts 500g | H1174: 0 | I1174: 302.63 | J1174: 0 | K1174: 0 | L1174: 0 | M1174: =H1174*I1174*(1-J1174) -> 0 | N1174: ="Q"&ROUNDUP(MONTH(B1174)/3,0) -> Q3 | O1174: 0 | P1174: =VLOOKUP(retail_sales_2023!C1174,customers!A:J,5,) -> Ranchi | Q1174: =VLOOKUP(C1174,customers!A:J,10,0) -> Premium
A1175: ORD001545 | B1175: 45119 | C1175: CUST0274 | D1175: Radhika Choudhury | E1175: South | F1175: Sports | G1175: Table Tennis Set | H1175: 1 | I1175: 6907.07 | J1175: 0.05 | K1175: 6561.72 | L1175: 1144.39 | M1175: =H1175*I1175*(1-J1175) -> 6561.7165 | N1175: ="Q"&ROUNDUP(MONTH(B1175)/3,0) -> Q3 | O1175: =(L1175/K1175)*100 -> 17.440397 | P1175: =VLOOKUP(retail_sales_2023!C1175,customers!A:J,5,) -> Chennai | Q1175: =VLOOKUP(C1175,customers!A:J,10,0) -> Premium
A1176: ORD007242 | B1176: 45182 | C1176: CUST0039 | D1176: Jonathan Dutta | E1176: West | F1176: Groceries | G1176: Sunflower Oil 1L | H1176: 8 | I1176: 504.1 | J1176: 0.15 | K1176: 3427.88 | L1176: 201.04 | M1176: =H1176*I1176*(1-J1176) -> 3427.88 | N1176: ="Q"&ROUNDUP(MONTH(B1176)/3,0) -> Q3 | O1176: =(L1176/K1176)*100 -> 5.8648494 | P1176: =VLOOKUP(retail_sales_2023!C1176,customers!A:J,5,) -> Nagpur | Q1176: =VLOOKUP(C1176,customers!A:J,10,0) -> Premium
A1177: ORD002625 | B1177: 45054 | C1177: CUST0016 | D1177: Hema Raja | E1177: South | F1177: Electronics | G1177: 4K Smart TV | H1177: 1 | I1177: 66882.89 | J1177: 0.15 | K1177: 56850.46 | L1177: 8045.99 | M1177: =H1177*I1177*(1-J1177) -> 56850.457 | N1177: ="Q"&ROUNDUP(MONTH(B1177)/3,0) -> Q2 | O1177: =(L1177/K1177)*100 -> 14.152902 | P1177: =VLOOKUP(retail_sales_2023!C1177,customers!A:J,5,) -> Hyderabad | Q1177: =VLOOKUP(C1177,customers!A:J,10,0) -> Regular
A1178: ORD006341 | B1178: 45270 | C1178: CUST0461 | D1178: Rushil Kakar | E1178: South | F1178: Toys | G1178: Remote Control Car | H1178: 1 | I1178: 1396.6 | J1178: 0 | K1178: 1396.6 | L1178: 313.15 | M1178: =H1178*I1178*(1-J1178) -> 1396.6 | N1178: ="Q"&ROUNDUP(MONTH(B1178)/3,0) -> Q4 | O1178: =(L1178/K1178)*100 -> 22.422311 | P1178: =VLOOKUP(retail_sales_2023!C1178,customers!A:J,5,) -> Hyderabad | Q1178: =VLOOKUP(C1178,customers!A:J,10,0) -> Regular
A1179: ORD004950 | B1179: 45011 | C1179: CUST0375 | D1179: Veer Halder | E1179: North | F1179: Sports | G1179: Running Shoes | H1179: 2 | I1179: 4220.73 | J1179: 0.05 | K1179: 8019.39 | L1179: 1341.82 | M1179: =H1179*I1179*(1-J1179) -> 8019.387 | N1179: ="Q"&ROUNDUP(MONTH(B1179)/3,0) -> Q1 | O1179: =(L1179/K1179)*100 -> 16.732195 | P1179: =VLOOKUP(retail_sales_2023!C1179,customers!A:J,5,) -> Chandigarh | Q1179: =VLOOKUP(C1179,customers!A:J,10,0) -> Premium
A1180: ORD008657 | B1180: 45118 | C1180: CUST0453 | D1180: Maanav Dâ€™Alia | E1180: East | F1180: Sports | G1180: Jump Rope | H1180: 1 | I1180: 5268.43 | J1180: 0.1 | K1180: 4741.59 | L1180: -171.6 | M1180: =H1180*I1180*(1-J1180) -> 4741.587 | N1180: ="Q"&ROUNDUP(MONTH(B1180)/3,0) -> Q3 | O1180: =(L1180/K1180)*100 -> -3.6190392 | P1180: =VLOOKUP(retail_sales_2023!C1180,customers!A:J,5,) -> Bhubaneswar | Q1180: =VLOOKUP(C1180,customers!A:J,10,0) -> Regular
A1181: ORD011328 | B1181: 44973 | C1181: CUST0273 | D1181: Tanmayi Pai | E1181: North | F1181: Groceries | G1181: Instant Coffee 200g | H1181: 10 | I1181: 112.97 | J1181: 0 | K1181: 1129.7 | L1181: 100.46 | M1181: =H1181*I1181*(1-J1181) -> 1129.7 | N1181: ="Q"&ROUNDUP(MONTH(B1181)/3,0) -> Q1 | O1181: =(L1181/K1181)*100 -> 8.8926264 | P1181: =VLOOKUP(retail_sales_2023!C1181,customers!A:J,5,) -> Lucknow | Q1181: =VLOOKUP(C1181,customers!A:J,10,0) -> Premium
A1182: ORD001904 | B1182: 45108 | C1182: CUST0181 | D1182: Chasmum Narang | E1182: West | F1182: Furniture | G1182: Bookshelf 5-Tier | H1182: 1 | I1182: 3111.21 | J1182: 0.1 | K1182: 2800.09 | L1182: 634.63 | M1182: =H1182*I1182*(1-J1182) -> 2800.089 | N1182: ="Q"&ROUNDUP(MONTH(B1182)/3,0) -> Q3 | O1182: =(L1182/K1182)*100 -> 22.664629 | P1182: =VLOOKUP(retail_sales_2023!C1182,customers!A:J,5,) -> Ahmedabad | Q1182: =VLOOKUP(C1182,customers!A:J,10,0) -> Premium
A1183: ORD010586 | B1183: 44957 | C1183: CUST0331 | D1183: Yashvi Manne | E1183: West | F1183: Toys | G1183: Building Blocks | H1183: 5 | I1183: 1053.51 | J1183: 0.05 | K1183: 5004.17 | L1183: 1061.94 | M1183: =H1183*I1183*(1-J1183) -> 5004.1725 | N1183: ="Q"&ROUNDUP(MONTH(B1183)/3,0) -> Q1 | O1183: =(L1183/K1183)*100 -> 21.221102 | P1183: =VLOOKUP(retail_sales_2023!C1183,customers!A:J,5,) -> Surat | Q1183: =VLOOKUP(C1183,customers!A:J,10,0) -> Premium
A1184: ORD004373 | B1184: 45070 | C1184: CUST0473 | D1184: Ranbir Jha | E1184: West | F1184: Electronics | G1184: Laptop 15" | H1184: 1 | I1184: 82707.33 | J1184: 0.2 | K1184: 66165.86 | L1184: 8785.06 | M1184: =H1184*I1184*(1-J1184) -> 66165.864 | N1184: ="Q"&ROUNDUP(MONTH(B1184)/3,0) -> Q2 | O1184: =(L1184/K1184)*100 -> 13.277331 | P1184: =VLOOKUP(retail_sales_2023!C1184,customers!A:J,5,) -> Pune | Q1184: =VLOOKUP(C1184,customers!A:J,10,0) -> Regular
A1185: ORD007976 | B1185: 45287 | C1185: CUST0307 | D1185: Ekani Tak | E1185: South | F1185: Groceries | G1185: Instant Coffee 200g | H1185: 8 | I1185: 62.77 | J1185: 0.1 | K1185: 451.94 | L1185: 46.66 | M1185: =H1185*I1185*(1-J1185) -> 451.944 | N1185: ="Q"&ROUNDUP(MONTH(B1185)/3,0) -> Q4 | O1185: =(L1185/K1185)*100 -> 10.324379 | P1185: =VLOOKUP(retail_sales_2023!C1185,customers!A:J,5,) -> Kochi | Q1185: =VLOOKUP(C1185,customers!A:J,10,0) -> Premium
A1186: ORD001720 | B1186: 45055 | C1186: CUST0114 | D1186: Gayathri Basak | E1186: East | F1186: Sports | G1186: Running Shoes | H1186: 4 | I1186: 3415.62 | J1186: 0.05 | K1186: 12979.36 | L1186: 3228.03 | M1186: =H1186*I1186*(1-J1186) -> 12979.356 | N1186: ="Q"&ROUNDUP(MONTH(B1186)/3,0) -> Q2 | O1186: =(L1186/K1186)*100 -> 24.870487 | P1186: =VLOOKUP(retail_sales_2023!C1186,customers!A:J,5,) -> Patna | Q1186: =VLOOKUP(C1186,customers!A:J,10,0) -> Premium
... A1318: ORD006542 | B1318: 45059 | C1318: CUST0306 | D1318: Unknown | E1318: West | F1318: Groceries | G1318: Instant Coffee 200g | H1318: 4 | I1318: 272.98 | J1318: 0.05 | K1318: 1037.32 | L1318: 90.29 | M1318: =H1318*I1318*(1-J1318) -> 1037.324 | N1318: ="Q"&ROUNDUP(MONTH(B1318)/3,0) -> Q2 | O1318: =(L1318/K1318)*100 -> 8.7041607 | P1318: =VLOOKUP(retail_sales_2023!C1318,customers!A:J,5,) -> Nagpur | Q1318: =VLOOKUP(C1318,customers!A:J,10,0) -> Premium
A1319: ORD006201 | B1319: 45100 | C1319: CUST0217 | D1319: Jonathan Madan | E1319: West | F1319: Groceries | G1319: Instant Coffee 200g | H1319: 0 | I1319: 261.78 | J1319: 0.1 | K1319: 0 | L1319: 0 | M1319: =H1319*I1319*(1-J1319) -> 0 | N1319: ="Q"&ROUNDUP(MONTH(B1319)/3,0) -> Q2 | O1319: 0 | P1319: =VLOOKUP(retail_sales_2023!C1319,customers!A:J,5,) -> Pune | Q1319: =VLOOKUP(C1319,customers!A:J,10,0) -> Premium
A1320: ORD008299 | B1320: 45183 | C1320: CUST0033 | D1320: Vasana Ahuja | E1320: East | F1320: Toys | G1320: Board Game Monopoly | H1320: 5 | I1320: 1091.19 | J1320: 0.05 | K1320: 5183.15 | L1320: -558.36 | M1320: =H1320*I1320*(1-J1320) -> 5183.1525 | N1320: ="Q"&ROUNDUP(MONTH(B1320)/3,0) -> Q3 | O1320: =(L1320/K1320)*100 -> -10.7726 | P1320: =VLOOKUP(retail_sales_2023!C1320,customers!A:J,5,) -> Ranchi | Q1320: =VLOOKUP(C1320,customers!A:J,10,0) -> Premium
...

Sheet customers
A1: Customer_ID | B1: Customer_Name | C1: Age | D1: Gender | E1: City | F1: Region | G1: Email | H1: Phone | I1: Join_Date | J1: Segment
A2: CUST0001 | B2: Aditya Bhakta | C2: 40 | D2: Female | E2: Delhi | F2: North | G2: alexander80@example.com | H2: 1828609487 | I2: 44466 | J2: Regular
A3: CUST0002 | B3: Nitara Dhawan | C3: 39 | D3: Male | E3: Chandigarh | F3: North | G3: suleekansh@example.com | H3: 3400231805 | I3: 44635 | J3: Premium
A4: CUST0003 | B4: Avi Johal | C4: 33 | D4: Female | E4: Patna | F4: East | G4: ghosemohammed@example.net | H4: 5471899671 | I4: 44578 | J4: Regular
A5: CUST0004 | B5: Lucky Aggarwal | C5: 62 | D5: Female | E5: Coimbatore | F5: South | G5: guhaamaira@example.com | H5: 1476165635 | I5: 44475 | J5: Premium
A6: CUST0005 | B6: Mason Dutt | C6: 34 | D6: Male | E6: Coimbatore | F6: South | G6: miteshdara@example.com | H6: 915171000000 | I6: 44282 | J6: Regular
A7: CUST0006 | B7: Yashica Nagi | C7: 44 | D7: Female | E7: Hyderabad | F7: South | G7: anitadube@example.org | H7: 917525000000 | I7: 44667 | J7: Regular
A8: CUST0007 | B8: Advika Gopal | C8: 57 | D8: Female | E8: Lucknow | F8: North | G8: aishani21@example.net | H8: 918951000000 | I8: 44713 | J8: Premium
A9: CUST0008 | B9: Sanya Memon | C9: 41 | D9: Female | E9: Lucknow | F9: North | G9: ganga35@example.net | H9: 7030304786 | I9: 44486 | J9: Occasional
A10: CUST0009 | B10: Gayathri Sankar | C10: 37 | D10: Male | E10: Surat | F10: West | G10: ridhi99@example.net | H10: 915324000000 | I10: 44484 | J10: Occasional
A11: CUST0010 | B11: Jack Goyal | C11: 60 | D11: Female | E11: Delhi | F11: North | G11: jkala@example.com | H11: 1172095314 | I11: 44208 | J11: Premium
A12: CUST0011 | B12: Xiti Dash | C12: 37 | D12: Other | E12: Jaipur | F12: North | G12: charvi89@example.org | H12: 3958350979 | I12: 44771 | J12: Regular
A13: CUST0012 | B13: Bina Sha | C13: 44 | D13: Male | E13: Chandigarh | F13: North | G13: jack02@example.net | H13: 9162411682 | I13: 44618 | J13: Occasional
... A501: CUST0500 | B501: Pooja Mand | C501: 52 | D501: Male | E501: Kochi | F501: South | G501: zansimane@example.net | H501: 6693060167 | I501: 44714 | J501: Premium

Sheet Monthly Target
A1: Region | B1: Category | C1: Month | D1: Month_Num | E1: Year | F1: Sales_Target | G1: Sales_Actual | H1: Achievement_Pct
A2: North | B2: Electronics | C2: Jan | D2: 1 | E2: 2023 | F2: 479513.19 | G2: 416944.16 | H2: 87
A3: North | B3: Electronics | C3: Feb | D3: 2 | E3: 2023 | F3: 571830.99 | G3: 495489.64 | H3: 86.6
A4: North | B4: Electronics | C4: Mar | D4: 3 | E4: 2023 | F4: 566601.65 | G4: 481131.18 | H4: 84.9
A5: North | B5: Electronics | C5: Apr | D5: 4 | E5: 2023 | F5: 500765.34 | G5: 544017.49 | H5: 108.6
A6: North | B6: Electronics | C6: May | D6: 5 | E6: 2023 | F6: 548309.22 | G6: 636262.75 | H6: 116
A7: North | B7: Electronics | C7: Jun | D7: 6 | E7: 2023 | F7: 552271.25 | G7: 574961.48 | H7: 104.1
A8: North | B8: Electronics | C8: Jul | D8: 7 | E8: 2023 | F8: 613946.43 | G8: 636131.49 | H8: 103.6
A9: North | B9: Electronics | C9: Aug | D9: 8 | E9: 2023 | F9: 559476.96 | G9: 473032.71 | H9: 84.5
A10: North | B10: Electronics | C10: Sep | D10: 9 | E10: 2023 | F10: 499031.94 | G10: 506329.71 | H10: 101.5
A11: North | B11: Electronics | C11: Oct | D11: 10 | E11: 2023 | F11: 673555.91 | G11: 518961.92 | H11: 77
A12: North | B12: Electronics | C12: Nov | D12: 11 | E12: 2023 | F12: 705294.54 | G12: 611755.9 | H12: 86.7
A13: North | B13: Electronics | C13: Dec | D13: 12 | E13: 2023 | F13: 753451.11 | G13: 638115.84 | H13: 84.7
... A337: West | B337: Toys | C337: Dec | D337: 12 | E337: 2023 | F337: 561972.21 | G337: 632010.13 | H337: 112.5

Sheet Monthly Trend
A3: Monthly Trend | B3: Column Labels
A4: Row Labels | B4: Jan | C4: Feb | D4: Mar | E4: Apr | F4: May | G4: Jun | H4: Jul | I4: Aug | J4: Sep | K4: Oct | L4: Nov | M4: Dec | N4: Grand Total
A5: Smartwatch | B5: 0.085830955 | C5: 0.16445474 | D5: 0.11514491 | E5: 0.09822174 | F5: 0.075444499 | G5: 0.10787905 | H5: 0.17217343 | I5: 0.10501928 | J5: 0.070196394 | K5: 0.12190264 | L5: 0.09786467 | M5: 0.1502429 | N5: 0.11381951
A6: USB-C Hub | B6: 0.10259464 | C6: 0.07785882 | D6: 0.15411958 | E6: 0.13289349 | F6: 0.11565431 | G6: 0.12535124 | H6: 0.071712662 | I6: 0.10379689 | J6: 0.13939756 | K6: 0.098020271 | L6: 0.08669454 | M6: 0.12254635 | N6: 0.11149972
A7: Gaming Mouse | B7: 0.11959411 | C7: 0.13385068 | D7: 0.07368924 | E7: 0.064844937 | F7: 0.079074669 | G7: 0.12939953 | H7: 0.11390706 | I7: 0.10057886 | J7: 0.16913706 | K7: 0.10688041 | L7: 0.11578721 | M7: 0.053080991 | N7: 0.10338214
A8: Smartphone X12 | B8: 0.11785513 | C8: 0.10741281 | D8: 0.072238953 | E8: 0.13207818 | F8: 0.082148033 | G8: 0.075779776 | H8: 0.078335798 | I8: 0.0704842 | J8: 0.12860299 | K8: 0.14525467 | L8: 0.093537546 | M8: 0.11672287 | N8: 0.10198056
A9: DSLR Camera | B9: 0.065345218 | C9: 0.092489172 | D9: 0.10348269 | E9: 0.081557847 | F9: 0.088026574 | G9: 0.11607466 | H9: 0.10398845 | I9: 0.082770259 | J9: 0.12325509 | K9: 0.14642313 | L9: 0.11505809 | M9: 0.10743992 | N9: 0.10154973
A10: Bluetooth Speaker | B10: 0.10591034 | C10: 0.11069696 | D10: 0.068687317 | E10: 0.1021722 | F10: 0.1251365 | G10: 0.11509628 | H10: 0.10321597 | I10: 0.10544368 | J10: 0.068197743 | K10: 0.09798696 | L10: 0.10245127 | M10: 0.091348015 | N10: 0.099579682
A11: Wireless Headphones | B11: 0.12796079 | C11: 0.050783041 | D11: 0.1066577 | E11: 0.083413966 | F11: 0.16032314 | G11: 0.14699304 | H11: 0.1012576 | I11: 0.079147758 | J11: 0.03560371 | K11: 0.092097686 | L11: 0.089858939 | M11: 0.076364213 | N11: 0.096072887
A12: Tablet Pro | B12: 0.11063535 | C12: 0.08495562 | D12: 0.088154259 | E12: 0.094829978 | F12: 0.10355232 | G12: 0.059107808 | H12: 0.1358617 | I12: 0.085882016 | J12: 0.087199932 | K12: 0.044597652 | L12: 0.10024039 | M12: 0.10754897 | N12: 0.09252139
A13: 4K Smart TV | B13: 0.10203427 | C13: 0.056221582 | D13: 0.14711033 | E13: 0.1097974 | F13: 0.093472054 | G13: 0.045714548 | H13: 0.059082143 | I13: 0.14589692 | J13: 0.077495075 | K13: 0.072791374 | L13: 0.1260854 | M13: 0.063791014 | N13: 0.091970676
A14: Laptop 15" | B14: 0.062239203 | C14: 0.12127659 | D14: 0.070715021 | E14: 0.10019026 | F14: 0.077167898 | G14: 0.078604079 | H14: 0.060465187 | I14: 0.12098012 | J14: 0.10091445 | K14: 0.074045211 | L14: 0.072421942 | M14: 0.11091476 | N14: 0.08762371
A15: Grand Total | B15: 1 | C15: 1 | D15: 1 | E15: 1 | F15: 1 | G15: 1 | H15: 1 | I15: 1 | J15: 1 | K15: 1 | L15: 1 | M15: 1 | N15: 1

Sheet sales by region & category
A3: Sum of Sales | B3: Column Labels
A4: Row Labels | B4: East | C4: North | D4: South | E4: West | F4: Grand Total
A5: Electronics | B5: 65737536 | C5: 72703282 | D5: 80109467 | E5: 77666210 | F5: 2.9621649e+08
A6: Furniture | B6: 17138443 | C6: 19742386 | D6: 19015020 | E6: 20393202 | F6: 76289050
A7: Sports | B7: 3248987.5 | C7: 4086190.1 | D7: 4599040.9 | E7: 4158238.5 | F7: 16092457
A8: Clothing | B8: 3995106.8 | C8: 3704436.6 | D8: 3935745.3 | E8: 4116469 | F8: 15751758
A9: Toys | B9: 1809723.9 | C9: 1562760.4 | D9: 1864400.3 | E9: 1664874.7 | F9: 6901759.3
A10: Groceries | B10: 1258422.4 | C10: 1464371.5 | D10: 1459382.8 | E10: 1419683.5 | F10: 5601860.2
A11: Books | B11: 342808.98 | C11: 364810 | D11: 410061.68 | E11: 431290.12 | F11: 1548970.8
A12: Grand Total | B12: 93531029 | C12: 1.0362824e+08 | D12: 1.1139312e+08 | E12: 1.0984997e+08 | F12: 4.1840235e+08

Sheet Target VS Actual
A1: Region | B1: (All)
A3: Month | B3: Sum of Sales_Target | C3: Sum of Sales_Actual | D3: Profit Flag
A4: Jan | B4: 13354606 | C4: 13872884 | D4: =GETPIVOTDATA("Sum of Sales_Actual",$A$3,"Month","Jan")-GETPIVOTDATA("Sum of Sales_Target",$A$3,"Month","Jan") -> 518277.7
A5: Feb | B5: 13266311 | C5: 13193652 | D5: =GETPIVOTDATA("Sum of Sales_Actual",$A$3,"Month","Feb")-GETPIVOTDATA("Sum of Sales_Target",$A$3,"Month","Feb") -> -72658.37
A6: Mar | B6: 13684420 | C6: 13302713 | D6: =GETPIVOTDATA("Sum of Sales_Actual",$A$3,"Month","Mar")-GETPIVOTDATA("Sum of Sales_Target",$A$3,"Month","Mar") -> -381707.54
A7: Apr | B7: 13555186 | C7: 13709245 | D7: =GETPIVOTDATA("Sum of Sales_Actual",$A$3,"Month","Apr")-GETPIVOTDATA("Sum of Sales_Target",$A$3,"Month","Apr") -> 154058.53
A8: May | B8: 13351079 | C8: 14064046 | D8: =GETPIVOTDATA("Sum of Sales_Actual",$A$3,"Month","May")-GETPIVOTDATA("Sum of Sales_Target",$A$3,"Month","May") -> 712967.02
A9: Jun | B9: 14816711 | C9: 14613462 | D9: =GETPIVOTDATA("Sum of Sales_Actual",$A$3,"Month","Jun")-GETPIVOTDATA("Sum of Sales_Target",$A$3,"Month","Jun") -> -203248.89 | G9: Regions | H9: Sum of Achievement_Pct
A10: Jul | B10: 15098457 | C10: 15733101 | D10: =GETPIVOTDATA("Sum of Sales_Actual",$A$3,"Month","Jul")-GETPIVOTDATA("Sum of Sales_Target",$A$3,"Month","Jul") -> 634644.43 | G10: East | H10: 0.25350779
A11: Aug | B11: 13414462 | C11: 13550280 | D11: =GETPIVOTDATA("Sum of Sales_Actual",$A$3,"Month","Aug")-GETPIVOTDATA("Sum of Sales_Target",$A$3,"Month","Aug") -> 135818.39 | G11: North | H11: 0.24832537
A12: Sep | B12: 13371441 | C12: 13297958 | D12: =GETPIVOTDATA("Sum of Sales_Actual",$A$3,"Month","Sep")-GETPIVOTDATA("Sum of Sales_Target",$A$3,"Month","Sep") -> -73482.49 | G12: South | H12: 0.24502184
A13: Oct | B13: 17582003 | C13: 17729357 | D13: =GETPIVOTDATA("Sum of Sales_Actual",$A$3,"Month","Oct")-GETPIVOTDATA("Sum of Sales_Target",$A$3,"Month","Oct") -> 147354.52 | G13: West | H13: 0.25314499
A14: Nov | B14: 17382209 | C14: 17152505 | D14: =GETPIVOTDATA("Sum of Sales_Actual",$A$3,"Month","Nov")-GETPIVOTDATA("Sum of Sales_Target",$A$3,"Month","Nov") -> -229704.39 | G14: Grand Total | H14: 1
A15: Dec | B15: 17683326 | C15: 18577008 | D15: =GETPIVOTDATA("Sum of Sales_Actual",$A$3,"Month","Dec")-GETPIVOTDATA("Sum of Sales_Target",$A$3,"Month","Dec") -> 893681.93
A16: Grand Total | B16: 1.7656021e+08 | C16: 1.7879621e+08 | D16: =SUM(D4:D15) -> 2236000.8
